{
  "name": "portfolio-site",
  "image": "mcr.microsoft.com/devcontainers/typescript-node:1-20",
  "features": {
    "ghcr.io/devcontainers/features/node:1": {
      "version": "20"
    }
  },
  "postCreateCommand": "npm install && npm run build",
  "customizations": {
    "vscode": {
      "settings": {
        "editor.formatOnSave": true,
        "typescript.tsserver.maxTsServerMemory": 4096
      },
      "extensions": [
        "dbaeumer.vscode-eslint",
        "esbenp.prettier-vscode",
        "bradlc.vscode-tailwindcss"
      ]
    }
  },
  "remoteUser": "node",
  "forwardPorts": [3000],
  "portsAttributes": {
    "3000": {
      "label": "Next.js Dev Server",
      "onAutoForward": "notify"
    }
  }
}
